{
	"@type":"Subset",
	"Name":"SYS.All Projects",
	"Elements":
	[
		{
			"@id":"Dimensions('Project')/Hierarchies('Project')/Elements('All Projects')"
		},
		{
			"@id":"Dimensions('Project')/Hierarchies('Project')/Elements('Unspec Project')"
		},
		{
			"@id":"Dimensions('Project')/Hierarchies('Project')/Elements('P100')"
		},
		{
			"@id":"Dimensions('Project')/Hierarchies('Project')/Elements('P200')"
		},
		{
			"@id":"Dimensions('Project')/Hierarchies('Project')/Elements('P300')"
		},
		{
			"@id":"Dimensions('Project')/Hierarchies('Project')/Elements('P111')"
		},
		{
			"@id":"Dimensions('Project')/Hierarchies('Project')/Elements('P110')"
		},
		{
			"@id":"Dimensions('Project')/Hierarchies('Project')/Elements('P120')"
		},
		{
			"@id":"Dimensions('Project')/Hierarchies('Project')/Elements('P130')"
		},
		{
			"@id":"Dimensions('Project')/Hierarchies('Project')/Elements('P210')"
		},
		{
			"@id":"Dimensions('Project')/Hierarchies('Project')/Elements('P220')"
		},
		{
			"@id":"Dimensions('Project')/Hierarchies('Project')/Elements('P230')"
		},
		{
			"@id":"Dimensions('Project')/Hierarchies('Project')/Elements('P310')"
		},
		{
			"@id":"Dimensions('Project')/Hierarchies('Project')/Elements('P320')"
		},
		{
			"@id":"Dimensions('Project')/Hierarchies('Project')/Elements('P330')"
		},
		{
			"@id":"Dimensions('Project')/Hierarchies('Project')/Elements('P112')"
		},
		{
			"@id":"Dimensions('Project')/Hierarchies('Project')/Elements('P113')"
		},
		{
			"@id":"Dimensions('Project')/Hierarchies('Project')/Elements('P121')"
		},
		{
			"@id":"Dimensions('Project')/Hierarchies('Project')/Elements('P122')"
		},
		{
			"@id":"Dimensions('Project')/Hierarchies('Project')/Elements('P123')"
		},
		{
			"@id":"Dimensions('Project')/Hierarchies('Project')/Elements('P131')"
		},
		{
			"@id":"Dimensions('Project')/Hierarchies('Project')/Elements('P132')"
		},
		{
			"@id":"Dimensions('Project')/Hierarchies('Project')/Elements('P133')"
		},
		{
			"@id":"Dimensions('Project')/Hierarchies('Project')/Elements('P211')"
		},
		{
			"@id":"Dimensions('Project')/Hierarchies('Project')/Elements('P212')"
		},
		{
			"@id":"Dimensions('Project')/Hierarchies('Project')/Elements('P213')"
		},
		{
			"@id":"Dimensions('Project')/Hierarchies('Project')/Elements('P221')"
		},
		{
			"@id":"Dimensions('Project')/Hierarchies('Project')/Elements('P222')"
		},
		{
			"@id":"Dimensions('Project')/Hierarchies('Project')/Elements('P223')"
		},
		{
			"@id":"Dimensions('Project')/Hierarchies('Project')/Elements('P231')"
		},
		{
			"@id":"Dimensions('Project')/Hierarchies('Project')/Elements('P232')"
		},
		{
			"@id":"Dimensions('Project')/Hierarchies('Project')/Elements('P233')"
		},
		{
			"@id":"Dimensions('Project')/Hierarchies('Project')/Elements('P311')"
		},
		{
			"@id":"Dimensions('Project')/Hierarchies('Project')/Elements('P312')"
		},
		{
			"@id":"Dimensions('Project')/Hierarchies('Project')/Elements('P313')"
		},
		{
			"@id":"Dimensions('Project')/Hierarchies('Project')/Elements('P321')"
		},
		{
			"@id":"Dimensions('Project')/Hierarchies('Project')/Elements('P322')"
		},
		{
			"@id":"Dimensions('Project')/Hierarchies('Project')/Elements('P323')"
		},
		{
			"@id":"Dimensions('Project')/Hierarchies('Project')/Elements('P331')"
		},
		{
			"@id":"Dimensions('Project')/Hierarchies('Project')/Elements('P332')"
		},
		{
			"@id":"Dimensions('Project')/Hierarchies('Project')/Elements('P333')"
		}
	]
}