{
	"@type":"Hierarchy",
	"Name":"Version",
	"Elements":
	[
		{
			"Name":"Version Consolidations",
			"Type":"Consolidated"
		},
		{
			"Name":"Reporting",
			"Type":"Consolidated"
		},
		{
			"Name":"Actual",
			"Type":"Numeric"
		},
		{
			"Name":"Budget",
			"Type":"Numeric"
		},
		{
			"Name":"Forecast",
			"Type":"Numeric"
		},
		{
			"Name":"Top Down Versions",
			"Type":"Consolidated"
		},
		{
			"Name":"Top Down Versions 1",
			"Type":"Numeric"
		},
		{
			"Name":"Static Versions",
			"Type":"Consolidated"
		},
		{
			"Name":"Budget 2016",
			"Type":"Numeric"
		},
		{
			"Name":"Dynamic Versions",
			"Type":"Consolidated"
		},
		{
			"Name":"Working Forecast",
			"Type":"Numeric"
		},
		{
			"Name":"Working Budget",
			"Type":"Numeric"
		},
		{
			"Name":"Variances",
			"Type":"Consolidated"
		},
		{
			"Name":"Actual vs Working Forecast",
			"Type":"Consolidated"
		},
		{
			"Name":"Actual vs Budget",
			"Type":"Consolidated"
		},
		{
			"Name":"System",
			"Type":"Consolidated"
		},
		{
			"Name":"No Version",
			"Type":"Numeric"
		},
		{
			"Name":"Dynamic Versions and Actual",
			"Type":"Consolidated"
		},
		{
			"Name":"Working Versions",
			"Type":"Consolidated"
		},
		{
			"Name":"Prompts",
			"Type":"Consolidated"
		},
		{
			"Name":"Test",
			"Type":"Numeric"
		}
	],
	"Edges":
	[
		{
			"ParentName":"Version Consolidations",
			"ComponentName":"Reporting",
			"Weight":1
		},
		{
			"ParentName":"Version Consolidations",
			"ComponentName":"System",
			"Weight":1
		},
		{
			"ParentName":"Reporting",
			"ComponentName":"Actual",
			"Weight":1
		},
		{
			"ParentName":"Reporting",
			"ComponentName":"Budget",
			"Weight":1
		},
		{
			"ParentName":"Reporting",
			"ComponentName":"Forecast",
			"Weight":1
		},
		{
			"ParentName":"Reporting",
			"ComponentName":"Top Down Versions",
			"Weight":1
		},
		{
			"ParentName":"Reporting",
			"ComponentName":"Static Versions",
			"Weight":1
		},
		{
			"ParentName":"Reporting",
			"ComponentName":"Dynamic Versions",
			"Weight":1
		},
		{
			"ParentName":"Reporting",
			"ComponentName":"Variances",
			"Weight":1
		},
		{
			"ParentName":"Top Down Versions",
			"ComponentName":"Top Down Versions 1",
			"Weight":1
		},
		{
			"ParentName":"Static Versions",
			"ComponentName":"Budget 2016",
			"Weight":1
		},
		{
			"ParentName":"Dynamic Versions",
			"ComponentName":"Working Forecast",
			"Weight":1
		},
		{
			"ParentName":"Dynamic Versions",
			"ComponentName":"Working Budget",
			"Weight":1
		},
		{
			"ParentName":"Variances",
			"ComponentName":"Actual vs Working Forecast",
			"Weight":1
		},
		{
			"ParentName":"Variances",
			"ComponentName":"Actual vs Budget",
			"Weight":1
		},
		{
			"ParentName":"Actual vs Working Forecast",
			"ComponentName":"Actual",
			"Weight":1
		},
		{
			"ParentName":"Actual vs Working Forecast",
			"ComponentName":"Working Forecast",
			"Weight":-1
		},
		{
			"ParentName":"Actual vs Budget",
			"ComponentName":"Actual",
			"Weight":1
		},
		{
			"ParentName":"Actual vs Budget",
			"ComponentName":"Budget",
			"Weight":-1
		},
		{
			"ParentName":"System",
			"ComponentName":"No Version",
			"Weight":1
		},
		{
			"ParentName":"System",
			"ComponentName":"Dynamic Versions and Actual",
			"Weight":1
		},
		{
			"ParentName":"System",
			"ComponentName":"Static Versions",
			"Weight":1
		},
		{
			"ParentName":"System",
			"ComponentName":"Working Versions",
			"Weight":1
		},
		{
			"ParentName":"System",
			"ComponentName":"Top Down Versions",
			"Weight":1
		},
		{
			"ParentName":"System",
			"ComponentName":"Variances",
			"Weight":1
		},
		{
			"ParentName":"System",
			"ComponentName":"Prompts",
			"Weight":1
		},
		{
			"ParentName":"System",
			"ComponentName":"Test",
			"Weight":1
		},
		{
			"ParentName":"Dynamic Versions and Actual",
			"ComponentName":"Dynamic Versions",
			"Weight":1
		},
		{
			"ParentName":"Dynamic Versions and Actual",
			"ComponentName":"Actual",
			"Weight":1
		},
		{
			"ParentName":"Working Versions",
			"ComponentName":"Working Forecast",
			"Weight":1
		},
		{
			"ParentName":"Working Versions",
			"ComponentName":"Working Budget",
			"Weight":1
		},
		{
			"ParentName":"Prompts",
			"ComponentName":"Actual",
			"Weight":1
		},
		{
			"ParentName":"Prompts",
			"ComponentName":"Budget",
			"Weight":1
		},
		{
			"ParentName":"Prompts",
			"ComponentName":"Forecast",
			"Weight":1
		},
		{
			"ParentName":"Prompts",
			"ComponentName":"Working Forecast",
			"Weight":1
		},
		{
			"ParentName":"Prompts",
			"ComponentName":"Working Budget",
			"Weight":1
		}
	],
	"Subsets@Code.links":
	[
		"Version.subsets/__BACKUP_All Members.json",
		"Version.subsets/All Members.json",
		"Version.subsets/Default.json",
		"Version.subsets/Level0.json",
		"Version.subsets/Monthly reporting version.json",
		"Version.subsets/Planning comparative version.json",
		"Version.subsets/Planning default version.json",
		"Version.subsets/Report Default.json",
		"Version.subsets/Reporting comparative version.json",
		"Version.subsets/Reporting default version.json",
		"Version.subsets/SYS.Actual.json",
		"Version.subsets/SYS.BI Prompts Update.json",
		"Version.subsets/SYS.Budget Versions.json",
		"Version.subsets/SYS.Consolidation_ToDisconnect.json",
		"Version.subsets/SYS.Dynamic Default.json",
		"Version.subsets/SYS.Dynamic Versions.json",
		"Version.subsets/SYS.Forecast Versions.json",
		"Version.subsets/SYS.Level0.json",
		"Version.subsets/SYS.No Version.json",
		"Version.subsets/SYS.Picklist.json",
		"Version.subsets/SYS.Planning Control.json",
		"Version.subsets/SYS.Source versions.json",
		"Version.subsets/SYS.Static Versions.json",
		"Version.subsets/SYS.Target Versions.json",
		"Version.subsets/SYS.Working Versions.json",
		"Version.subsets/tp_931f17de-67c3-4462-b2f8-b5f9376c09f2.json",
		"Version.subsets/tp_{aed001f4-bd34-4537-840d-c8e04bb097e5}.json",
		"Version.subsets/Working Budget comparative version.json",
		"Version.subsets/Working Forecast comparative version.json",
		"Version.subsets/}CTK_Viewbuild Allocation Assumptions.json",
		"Version.subsets/}CTK_Viewbuild Allocation Assumptions_AsmPools.json",
		"Version.subsets/}CTK_Viewbuild Allocation Assumptions_L0.json",
		"Version.subsets/}CTK_Viewbuild Allocation Assumptions Zero.json",
		"Version.subsets/}CTK_Viewbuild Allocation Definitions.json",
		"Version.subsets/}CTK_Viewbuild Allocation Definitions_L0.json",
		"Version.subsets/}CTK_Viewbuild Allocation Definitions Zero.json",
		"Version.subsets/}CTK_Viewbuild Allocations.json",
		"Version.subsets/}CTK_Viewbuild Allocations_Alloc.json",
		"Version.subsets/}CTK_Viewbuild Allocations_L0.json",
		"Version.subsets/}CTK_Viewbuild Allocations Alloc Zero.json",
		"Version.subsets/}CTK_Viewbuild Allocations Zero.json",
		"Version.subsets/}CTK_Viewbuild Assumptions.json",
		"Version.subsets/}CTK_Viewbuild Assumptions_L0.json",
		"Version.subsets/}CTK_Viewbuild Assumptions Zero.json",
		"Version.subsets/}CTK_Viewbuild Capex.json",
		"Version.subsets/}CTK_Viewbuild Capex_L0.json",
		"Version.subsets/}CTK_Viewbuild Capex Zero.json",
		"Version.subsets/}CTK_Viewbuild Cost Pools.json",
		"Version.subsets/}CTK_Viewbuild Financials.json",
		"Version.subsets/}CTK_Viewbuild Financials_Alloc.json",
		"Version.subsets/}CTK_Viewbuild Financials_Alloc_L0.json",
		"Version.subsets/}CTK_Viewbuild Financials_Data.Financials.Load.json",
		"Version.subsets/}CTK_Viewbuild Financials_Data.PL.Load.json",
		"Version.subsets/}CTK_Viewbuild Financials_L0.json",
		"Version.subsets/}CTK_Viewbuild Financials Alloc.json",
		"Version.subsets/}CTK_Viewbuild Financials Alloc_L0.json",
		"Version.subsets/}CTK_Viewbuild Financials Zero.json",
		"Version.subsets/}CTK_Viewbuild GM Assumptions.json",
		"Version.subsets/}CTK_Viewbuild GM Assumptions_L0.json",
		"Version.subsets/}CTK_Viewbuild GM Assumptions Zero.json",
		"Version.subsets/}CTK_Viewbuild Gross Margin.json",
		"Version.subsets/}CTK_Viewbuild Gross Margin_Data.GrossMargin.Load.json",
		"Version.subsets/}CTK_Viewbuild Gross Margin_L0.json",
		"Version.subsets/}CTK_Viewbuild Gross Margin Zero.json",
		"Version.subsets/}CTK_Viewbuild Metrics.json",
		"Version.subsets/}CTK_Viewbuild Metrics_L0.json",
		"Version.subsets/}CTK_Viewbuild Metrics Zero.json",
		"Version.subsets/}CTK_Viewbuild Personnel.json",
		"Version.subsets/}CTK_Viewbuild Personnel_Data.Personnel.Load.json",
		"Version.subsets/}CTK_Viewbuild Personnel_L0.json",
		"Version.subsets/}CTK_Viewbuild Personnel Zero.json",
		"Version.subsets/}CTK_Viewbuild Phasing Profiles.json",
		"Version.subsets/}CTK_Viewbuild Phasing Profiles_L0.json",
		"Version.subsets/}CTK_Viewbuild Phasing Profiles Zero.json",
		"Version.subsets/}CTK_Viewbuild PL.json",
		"Version.subsets/}CTK_Viewbuild PL_Data.PL.Load.json",
		"Version.subsets/}CTK_Viewbuild PL_L0.json",
		"Version.subsets/}CTK_Viewbuild PL Workings.json",
		"Version.subsets/}CTK_Viewbuild PL Workings_L0.json",
		"Version.subsets/}CTK_Viewbuild PL Workings Zero.json",
		"Version.subsets/}CTK_Viewbuild PL Zero.json",
		"Version.subsets/}CTK_Viewbuild Reserves.json",
		"Version.subsets/}CTK_Viewbuild Reserves_L0.json",
		"Version.subsets/}CTK_Viewbuild Reserves Zero.json",
		"Version.subsets/}CTK_Viewbuild Workings.json",
		"Version.subsets/}CTK_Viewbuild Workings_L0.json",
		"Version.subsets/}CTK_Viewbuild Workings Zero.json",
		"Version.subsets/}CTK_ViewCopy Allocation Definitions.json",
		"Version.subsets/}CTK_ViewCopy Allocations.json",
		"Version.subsets/}CTK_ViewCopy Assumptions.json",
		"Version.subsets/}CTK_ViewCopy Capex.json",
		"Version.subsets/}CTK_ViewCopy Cost Pools.json",
		"Version.subsets/}CTK_ViewCopy Financials.json",
		"Version.subsets/}CTK_ViewCopy Gross Margin.json",
		"Version.subsets/}CTK_ViewCopy Metrics.json",
		"Version.subsets/}CTK_ViewCopy Personnel.json",
		"Version.subsets/}CTK_ViewCopy Phasing Profiles.json",
		"Version.subsets/}CTK_ViewCopy PL.json",
		"Version.subsets/}CTK_ViewCopy PL Workings.json",
		"Version.subsets/}CTK_ViewCopy Project.json"
	]
}