{
	"@type":"Hierarchy",
	"Name":"Menu Items",
	"Elements":
	[
		{
			"Name":"Main Menu",
			"Type":"Consolidated"
		},
		{
			"Name":"Planning & Forecasting",
			"Type":"Consolidated"
		},
		{
			"Name":"Profit and Loss Entry",
			"Type":"Numeric"
		},
		{
			"Name":"Capital Expenditure Entry",
			"Type":"Numeric"
		},
		{
			"Name":"Personnel Entry",
			"Type":"Numeric"
		},
		{
			"Name":"Admin",
			"Type":"Consolidated"
		},
		{
			"Name":"Admin activities",
			"Type":"Numeric"
		},
		{
			"Name":"Assumption maintenance",
			"Type":"Numeric"
		},
		{
			"Name":"Capex assumptions",
			"Type":"Numeric"
		},
		{
			"Name":"Hierarchy maintenance",
			"Type":"Numeric"
		},
		{
			"Name":"Personnel assumptions",
			"Type":"Numeric"
		},
		{
			"Name":"Setup screen",
			"Type":"Numeric"
		},
		{
			"Name":"Main Menu Dynamic",
			"Type":"Consolidated"
		},
		{
			"Name":"HR",
			"Type":"Consolidated"
		},
		{
			"Name":"Expenditure",
			"Type":"Numeric"
		},
		{
			"Name":"Revenue",
			"Type":"Numeric"
		},
		{
			"Name":"Timesheets",
			"Type":"Numeric"
		},
		{
			"Name":"PL",
			"Type":"Consolidated"
		},
		{
			"Name":"Reporting",
			"Type":"Consolidated"
		},
		{
			"Name":"Balance Sheet",
			"Type":"Numeric"
		},
		{
			"Name":"Cash Flow",
			"Type":"Numeric"
		},
		{
			"Name":"Profit and Loss",
			"Type":"Numeric"
		},
		{
			"Name":"Account by Project Report",
			"Type":"Numeric"
		},
		{
			"Name":"Profit and Loss Variance",
			"Type":"Numeric"
		},
		{
			"Name":"Balance Sheet and Cash Flow Variance",
			"Type":"Numeric"
		},
		{
			"Name":"Capex Report",
			"Type":"Numeric"
		},
		{
			"Name":"Personnel Report",
			"Type":"Numeric"
		},
		{
			"Name":"testGroup",
			"Type":"Consolidated"
		},
		{
			"Name":"testGroupChild",
			"Type":"Consolidated"
		},
		{
			"Name":"Links & Documentation",
			"Type":"Consolidated"
		},
		{
			"Name":"Cortell Support",
			"Type":"Numeric"
		},
		{
			"Name":"test",
			"Type":"Consolidated"
		}
	],
	"Edges":
	[
		{
			"ParentName":"Main Menu",
			"ComponentName":"Planning & Forecasting",
			"Weight":1
		},
		{
			"ParentName":"Main Menu",
			"ComponentName":"Reporting",
			"Weight":1
		},
		{
			"ParentName":"Main Menu",
			"ComponentName":"Admin",
			"Weight":1
		},
		{
			"ParentName":"Planning & Forecasting",
			"ComponentName":"Profit and Loss Entry",
			"Weight":1
		},
		{
			"ParentName":"Planning & Forecasting",
			"ComponentName":"Capital Expenditure Entry",
			"Weight":1
		},
		{
			"ParentName":"Planning & Forecasting",
			"ComponentName":"Personnel Entry",
			"Weight":1
		},
		{
			"ParentName":"Admin",
			"ComponentName":"Admin activities",
			"Weight":1
		},
		{
			"ParentName":"Admin",
			"ComponentName":"Assumption maintenance",
			"Weight":1
		},
		{
			"ParentName":"Admin",
			"ComponentName":"Capex assumptions",
			"Weight":1
		},
		{
			"ParentName":"Admin",
			"ComponentName":"Hierarchy maintenance",
			"Weight":1
		},
		{
			"ParentName":"Admin",
			"ComponentName":"Personnel assumptions",
			"Weight":1
		},
		{
			"ParentName":"Admin",
			"ComponentName":"Setup screen",
			"Weight":1
		},
		{
			"ParentName":"Main Menu Dynamic",
			"ComponentName":"HR",
			"Weight":1
		},
		{
			"ParentName":"Main Menu Dynamic",
			"ComponentName":"PL",
			"Weight":1
		},
		{
			"ParentName":"HR",
			"ComponentName":"Expenditure",
			"Weight":1
		},
		{
			"ParentName":"HR",
			"ComponentName":"Revenue",
			"Weight":1
		},
		{
			"ParentName":"HR",
			"ComponentName":"Timesheets",
			"Weight":1
		},
		{
			"ParentName":"PL",
			"ComponentName":"Reporting",
			"Weight":1
		},
		{
			"ParentName":"PL",
			"ComponentName":"testGroup",
			"Weight":1
		},
		{
			"ParentName":"PL",
			"ComponentName":"testGroupChild",
			"Weight":1
		},
		{
			"ParentName":"Reporting",
			"ComponentName":"Balance Sheet",
			"Weight":1
		},
		{
			"ParentName":"Reporting",
			"ComponentName":"Cash Flow",
			"Weight":1
		},
		{
			"ParentName":"Reporting",
			"ComponentName":"Profit and Loss",
			"Weight":1
		},
		{
			"ParentName":"Reporting",
			"ComponentName":"Account by Project Report",
			"Weight":1
		},
		{
			"ParentName":"Reporting",
			"ComponentName":"Profit and Loss Variance",
			"Weight":1
		},
		{
			"ParentName":"Reporting",
			"ComponentName":"Balance Sheet and Cash Flow Variance",
			"Weight":1
		},
		{
			"ParentName":"Reporting",
			"ComponentName":"Capex Report",
			"Weight":1
		},
		{
			"ParentName":"Reporting",
			"ComponentName":"Personnel Report",
			"Weight":1
		},
		{
			"ParentName":"testGroupChild",
			"ComponentName":"Links & Documentation",
			"Weight":1
		},
		{
			"ParentName":"testGroupChild",
			"ComponentName":"test",
			"Weight":1
		},
		{
			"ParentName":"Links & Documentation",
			"ComponentName":"Cortell Support",
			"Weight":1
		}
	],
	"Subsets@Code.links":
	[
		"Menu Items.subsets/Default.json",
		"Menu Items.subsets/Level0.json",
		"Menu Items.subsets/SYS.Budget Tasks.json",
		"Menu Items.subsets/SYS.Forecast Items.json",
		"Menu Items.subsets/SYS.Forecast Tasks.json",
		"Menu Items.subsets/SYS.Level0.json",
		"Menu Items.subsets/SYS.MenuForecast.json",
		"Menu Items.subsets/SYS.MenuItems.json"
	]
}